{
  "users": [
    {
      "id": 1,
      "accountNumber": "12345",
      "pin": "1234",
      "balance": 95499
    },
    {
      "id": 2,
      "accountNumber": "124556",
      "pin": "4567",
      "balance": 9999
    }
  ],
  "transactions": [
    {
      "id": 1,
      "userId": 1,
      "date": "2024-11-20T10:00:00Z",
      "description": "Deposit",
      "amount": 2000
    },
    {
      "id": 2,
      "userId": 1,
      "date": "2024-11-20T12:00:00Z",
      "description": "Withdrawal",
      "amount": -500
    },
    {
      "userId": 1,
      "date": "2024-11-21T05:46:49.408Z",
      "description": "Deposit",
      "amount": 100,
      "id": 3
    },
    {
      "userId": 1,
      "date": "2024-11-21T05:48:18.586Z",
      "description": "Withdraw",
      "amount": 2000,
      "id": 4
    },
    {
      "userId": 1,
      "date": "2024-11-21T08:03:34.446Z",
      "description": "Withdraw",
      "amount": 400,
      "id": 5
    },
    {
      "userId": 1,
      "date": "2024-11-21T08:04:55.157Z",
      "description": "Withdraw",
      "amount": -500,
      "id": 6
    },
    {
      "userId": 1,
      "date": "2024-11-21T08:06:31.635Z",
      "description": "Withdraw",
      "amount": -900,
      "id": 7
    },
    {
      "userId": 1,
      "date": "2024-11-21T08:31:29.324Z",
      "description": "Withdraw",
      "amount": -800,
      "id": 8
    },
    {
      "userId": 1,
      "date": "2024-11-21T08:33:09.238Z",
      "description": "Withdraw",
      "amount": -100,
      "id": 9
    }
  ]
}